{"chunk_definitions":[{"chunk_id":"csetup_chunk","chunk_label":"setup","document_id":"E34F102E","expansion_state":0,"options":{"engine":"r","include":false,"label":"setup"},"row":9,"row_count":1,"visible":true},{"chunk_id":"c80o8s13p2xjr","chunk_label":"unnamed-chunk-1","document_id":"E34F102E","expansion_state":0,"options":{"engine":"r","label":"unnamed-chunk-3"},"row":17,"row_count":1,"visible":true},{"chunk_id":"ce70y8qtzzmpc","chunk_label":"unnamed-chunk-12","document_id":"E34F102E","expansion_state":0,"options":{"engine":"r","label":"unnamed-chunk-17"},"row":81,"row_count":1,"visible":true},{"chunk_id":"c53moh6enrq13","chunk_label":"unnamed-chunk-14","document_id":"E34F102E","expansion_state":0,"options":{"engine":"r","label":"unnamed-chunk-22"},"row":89,"row_count":1,"visible":true}],"default_chunk_options":{"echo":true},"doc_write_time":1586327189,"working_dir":null}